README.md
setup.py
bin/pyschieber
pyschieber/__init__.py
pyschieber/card.py
pyschieber/dealer.py
pyschieber/deck.py
pyschieber/game.py
pyschieber/stich.py
pyschieber/suit.py
pyschieber/team.py
pyschieber/tournament.py
pyschieber/trumpf.py
pyschieber.egg-info/PKG-INFO
pyschieber.egg-info/SOURCES.txt
pyschieber.egg-info/dependency_links.txt
pyschieber.egg-info/top_level.txt
pyschieber/example/__init__.py
pyschieber/example/main.py
pyschieber/example/server_launcher.py
pyschieber/helpers/__init__.py
pyschieber/helpers/game_helper.py
pyschieber/player/__init__.py
pyschieber/player/base_player.py
pyschieber/player/cli_player.py
pyschieber/player/random_player.py
pyschieber/player/challenge_player/__init__.py
pyschieber/player/challenge_player/challenge_player.py
pyschieber/player/challenge_player/strategy/__init__.py
pyschieber/player/challenge_player/strategy/card_counter.py
pyschieber/player/challenge_player/strategy/jass_strategy.py
pyschieber/player/challenge_player/strategy/flags/__init__.py
pyschieber/player/challenge_player/strategy/flags/doesnt_habe_card_flag.py
pyschieber/player/challenge_player/strategy/flags/falied_to_serve_suit_flag.py
pyschieber/player/challenge_player/strategy/flags/previously_had_stich_flag.py
pyschieber/player/challenge_player/strategy/flags/suit_verworfen_flag.py
pyschieber/player/challenge_player/strategy/mode/__init__.py
pyschieber/player/challenge_player/strategy/mode/bottom_up_mode.py
pyschieber/player/challenge_player/strategy/mode/mode.py
pyschieber/player/challenge_player/strategy/mode/top_down_mode.py
pyschieber/player/challenge_player/strategy/mode/trumpf_color_mode.py
pyschieber/player/challenge_player/strategy/mode/uncolored_trumpf.py
pyschieber/player/greedy_player/__init__.py
pyschieber/player/greedy_player/greedy_player.py
pyschieber/player/greedy_player/trumpf_decision.py
pyschieber/player/server_player/__init__.py
pyschieber/player/server_player/server_player.py
pyschieber/player/server_player/helpers/__init__.py
pyschieber/player/server_player/helpers/messages.py
pyschieber/player/server_player/helpers/server_cards.py
