Metadata-Version: 1.0
Name: pyschieber
Version: 1.3.0
Summary: pyschieber is a terminal application of the popular swiss card game Schieber and provides an API to the game
Home-page: https://github.com/Murthy10/pyschieber
Author: Samuel Kurath
Author-email: samuel.kurath@gmail.com
License: MIT
Platform: UNKNOWN
